[{"hh_id":1421689,"hh_has_child":false,"hh_members":2,"hh_cars":0,"hh_income":1936,"members":[{"total_distance":50853.938,"p_sex":1,"scheme_id":5109,"p_age":30,"activities":[-1,50,522,700],"p_id":1784876,"possibilities":["HOME","SHOPPING","SETTLEMENT","HOME"],"p_abo":true,"p_group":14},{"total_distance":31727.424,"p_sex":2,"scheme_id":29189,"p_age":25,"activities":[-1,722,531,720,711],"p_id":1784877,"possibilities":["HOME","LEISURE","HOME","LEISURE","HOME"],"p_abo":false,"p_group":2}]},{"hh_id":1421711,"hh_has_child":false,"hh_members":2,"hh_cars":1,"hh_income":1453,"members":[{"total_distance":123900.336,"p_sex":2,"scheme_id":17917,"p_age":40,"activities":[-1,640,299,640,531,640,531,640,299],"p_id":1784921,"possibilities":["HOME","LEISURE","HOME","LEISURE","HOME","LEISURE","HOME","LEISURE","HOME"],"p_abo":true,"p_group":15},{"total_distance":9489.83,"p_sex":1,"scheme_id":31301,"p_age":36,"activities":[-1,410,299],"p_id":1784920,"possibilities":["HOME","EDUCATION","HOME"],"p_abo":true,"p_group":13}]},{"hh_id":1421716,"hh_has_child":false,"hh_members":2,"hh_cars":2,"hh_income":1771,"members":[{"total_distance":6223.092,"p_sex":1,"scheme_id":17152,"p_age":66,"activities":[-1,800,10,631,531],"p_id":1784930,"possibilities":["HOME","LEISURE","HOME","SETTLEMENT","HOME"],"p_abo":false,"p_group":25}]},{"hh_id":1421718,"hh_has_child":false,"hh_members":2,"hh_cars":1,"hh_income":2150,"members":[{"total_distance":22277.477,"p_sex":2,"scheme_id":31223,"p_age":45,"activities":[-1,50,50,611,10,740,10],"p_id":1784935,"possibilities":["HOME","SHOPPING","SHOPPING","SETTLEMENT","HOME","OTHER","HOME"],"p_abo":false,"p_group":19},{"total_distance":5957.9136,"p_sex":1,"scheme_id":20730,"p_age":31,"activities":[-1,722,700],"p_id":1784934,"possibilities":["HOME","LEISURE","HOME"],"p_abo":true,"p_group":13}]},{"hh_id":1421730,"hh_has_child":false,"hh_members":2,"hh_cars":0,"hh_income":1961,"members":[{"total_distance":5791.7017,"p_sex":2,"scheme_id":29092,"p_age":61,"activities":[-1,740,10,50,531,50,700],"p_id":1784959,"possibilities":["HOME","OTHER","HOME","SHOPPING","HOME","SHOPPING","HOME"],"p_abo":false,"p_group":24},{"total_distance":39950.53,"p_sex":1,"scheme_id":14206,"p_age":46,"activities":[-1,211,50,700,211,531,722,50,700],"p_id":1784958,"possibilities":["HOME","JOB","SHOPPING","HOME","JOB","HOME","LEISURE","SHOPPING","HOME"],"p_abo":true,"p_group":18}]}]