[{"hh_id":1366656,"hh_has_child":true,"hh_members":3,"hh_cars":1,"hh_income":3542,"members":[{"total_distance":32763.314,"p_sex":2,"scheme_id":20646,"p_age":42,"activities":[-1,50,10,522,531,522,10,640,531],"p_id":1671000,"possibilities":["HOME","SHOPPING","HOME","SETTLEMENT","HOME","SETTLEMENT","HOME","LEISURE","HOME"],"p_abo":false,"p_group":11},{"total_distance":31057.537,"p_sex":2,"scheme_id":34033,"p_age":11,"activities":[-1,410,531,721,531],"p_id":1670999,"possibilities":["HOME","EDUCATION","HOME","LEISURE","HOME"],"p_abo":true,"p_group":1}]},{"hh_id":1366689,"hh_has_child":false,"hh_members":3,"hh_cars":1,"hh_income":2310,"members":[{"total_distance":24501.404,"p_sex":2,"scheme_id":17622,"p_age":53,"activities":[-1,640,700,799,711],"p_id":1671099,"possibilities":["HOME","LEISURE","HOME","OTHER","HOME"],"p_abo":false,"p_group":19},{"total_distance":0.0,"p_sex":1,"scheme_id":3846,"p_age":16,"activities":[],"p_id":1671098,"possibilities":[],"p_abo":true,"p_group":6},{"total_distance":10963.1455,"p_sex":2,"scheme_id":20710,"p_age":14,"activities":[-1,410,531,631,721,531],"p_id":1671097,"possibilities":["HOME","EDUCATION","HOME","SETTLEMENT","LEISURE","HOME"],"p_abo":true,"p_group":1}]},{"hh_id":1366693,"hh_has_child":false,"hh_members":3,"hh_cars":1,"hh_income":966,"members":[{"total_distance":30054.234,"p_sex":2,"scheme_id":1272,"p_age":30,"activities":[-1,522,724,50,700],"p_id":1671111,"possibilities":["HOME","SETTLEMENT","LEISURE","SHOPPING","HOME"],"p_abo":false,"p_group":15},{"total_distance":32607.447,"p_sex":2,"scheme_id":19928,"p_age":11,"activities":[-1,640,700,720,700],"p_id":1671110,"possibilities":["HOME","LEISURE","HOME","LEISURE","HOME"],"p_abo":true,"p_group":1},{"total_distance":0.0,"p_sex":2,"scheme_id":26527,"p_age":7,"activities":[],"p_id":1671109,"possibilities":[],"p_abo":true,"p_group":1}]},{"hh_id":1366709,"hh_has_child":true,"hh_members":3,"hh_cars":0,"hh_income":1337,"members":[{"total_distance":80135.76,"p_sex":2,"scheme_id":23007,"p_age":39,"activities":[-1,722,531,211,512,522,512,722,531],"p_id":1671159,"possibilities":["HOME","LEISURE","HOME","JOB","LEISURE","SETTLEMENT","LEISURE","LEISURE","HOME"],"p_abo":false,"p_group":12},{"total_distance":14792.453,"p_sex":1,"scheme_id":20406,"p_age":9,"activities":[-1,410,531],"p_id":1671157,"possibilities":["HOME","EDUCATION","HOME"],"p_abo":true,"p_group":1}]},{"hh_id":1366710,"hh_has_child":false,"hh_members":3,"hh_cars":0,"hh_income":996,"members":[{"total_distance":42282.617,"p_sex":2,"scheme_id":21348,"p_age":33,"activities":[-1,410,700,522,50,700,800,700],"p_id":1671162,"possibilities":["HOME","EDUCATION","HOME","SETTLEMENT","SHOPPING","HOME","LEISURE","HOME"],"p_abo":false,"p_group":16},{"total_distance":10198.655,"p_sex":2,"scheme_id":34005,"p_age":14,"activities":[-1,522,50,720,700],"p_id":1671160,"possibilities":["HOME","SETTLEMENT","SHOPPING","LEISURE","HOME"],"p_abo":true,"p_group":1},{"total_distance":40277.688,"p_sex":1,"scheme_id":23485,"p_age":10,"activities":[-1,410,531,522,700,721,531],"p_id":1671161,"possibilities":["HOME","EDUCATION","HOME","SETTLEMENT","HOME","LEISURE","HOME"],"p_abo":true,"p_group":1}]}]