[{"hh_id":1153643,"hh_has_child":false,"hh_members":1,"hh_cars":0,"hh_income":1157,"members":[{"total_distance":35189.81,"p_sex":2,"scheme_id":25743,"p_age":30,"activities":[-1,611,50,700,32,10,631,700],"p_id":1286917,"possibilities":["HOME","SETTLEMENT","SHOPPING","HOME","SETTLEMENT","HOME","SETTLEMENT","HOME"],"p_abo":false,"p_group":12}]},{"hh_id":1153661,"hh_has_child":false,"hh_members":1,"hh_cars":1,"hh_income":1486,"members":[{"total_distance":37410.7,"p_sex":2,"scheme_id":26014,"p_age":30,"activities":[-1,211,211,522,700,300,10],"p_id":1286935,"possibilities":["HOME","JOB","JOB","SETTLEMENT","HOME","LEISURE","HOME"],"p_abo":true,"p_group":11}]},{"hh_id":1153662,"hh_has_child":false,"hh_members":1,"hh_cars":1,"hh_income":768,"members":[{"total_distance":58452.805,"p_sex":2,"scheme_id":31141,"p_age":40,"activities":[-1,300,511],"p_id":1286936,"possibilities":["HOME","LEISURE","HOME"],"p_abo":true,"p_group":15}]},{"hh_id":1153678,"hh_has_child":false,"hh_members":1,"hh_cars":0,"hh_income":2954,"members":[{"total_distance":15686.459,"p_sex":2,"scheme_id":14136,"p_age":25,"activities":[-1,722,700],"p_id":1286952,"possibilities":["HOME","LEISURE","HOME"],"p_abo":false,"p_group":12}]},{"hh_id":1153679,"hh_has_child":false,"hh_members":1,"hh_cars":1,"hh_income":2192,"members":[{"total_distance":3390.2402,"p_sex":2,"scheme_id":7456,"p_age":42,"activities":[-1,50,531],"p_id":1286953,"possibilities":["HOME","SHOPPING","HOME"],"p_abo":false,"p_group":11}]}]