[{"hh_id":1553143,"hh_has_child":false,"hh_members":4,"hh_cars":2,"hh_income":1566,"members":[{"total_distance":4529.9556,"p_sex":2,"scheme_id":5693,"p_age":55,"activities":[-1,722,711],"p_id":1956223,"possibilities":["HOME","LEISURE","HOME"],"p_abo":false,"p_group":23},{"total_distance":9925.645,"p_sex":1,"scheme_id":35380,"p_age":55,"activities":[-1,50,700,522,531,722,10],"p_id":1956224,"possibilities":["HOME","SHOPPING","HOME","SETTLEMENT","HOME","LEISURE","HOME"],"p_abo":false,"p_group":21},{"total_distance":0.0,"p_sex":2,"scheme_id":15373,"p_age":16,"activities":[],"p_id":1956221,"possibilities":[],"p_abo":true,"p_group":1},{"total_distance":5702.8687,"p_sex":1,"scheme_id":22311,"p_age":16,"activities":[-1,410,531,723,711],"p_id":1956222,"possibilities":["HOME","EDUCATION","HOME","LEISURE","HOME"],"p_abo":true,"p_group":1}]},{"hh_id":1553152,"hh_has_child":true,"hh_members":4,"hh_cars":2,"hh_income":4867,"members":[{"total_distance":10830.514,"p_sex":1,"scheme_id":29440,"p_age":42,"activities":[-1,721,700,721,50,720,10],"p_id":1956260,"possibilities":["HOME","LEISURE","HOME","LEISURE","SHOPPING","LEISURE","HOME"],"p_abo":false,"p_group":9}]},{"hh_id":1553164,"hh_has_child":false,"hh_members":4,"hh_cars":1,"hh_income":3002,"members":[{"total_distance":28158.393,"p_sex":2,"scheme_id":29992,"p_age":44,"activities":[-1,211,700,800,10,50,10,522,211,10],"p_id":1956307,"possibilities":["HOME","JOB","HOME","LEISURE","HOME","SHOPPING","HOME","SETTLEMENT","JOB","HOME"],"p_abo":true,"p_group":11},{"total_distance":4871.909,"p_sex":1,"scheme_id":9947,"p_age":44,"activities":[-1,211,700],"p_id":1956308,"possibilities":["HOME","JOB","HOME"],"p_abo":false,"p_group":9},{"total_distance":25356.734,"p_sex":1,"scheme_id":24018,"p_age":17,"activities":[-1,410,531,720,700],"p_id":1956305,"possibilities":["HOME","EDUCATION","HOME","LEISURE","HOME"],"p_abo":true,"p_group":1},{"total_distance":36619.957,"p_sex":1,"scheme_id":35234,"p_age":9,"activities":[-1,50,50,10,410,631,700],"p_id":1956306,"possibilities":["HOME","SHOPPING","SHOPPING","HOME","EDUCATION","SETTLEMENT","HOME"],"p_abo":true,"p_group":1}]},{"hh_id":1553181,"hh_has_child":true,"hh_members":4,"hh_cars":2,"hh_income":5993,"members":[{"total_distance":12142.353,"p_sex":1,"scheme_id":32964,"p_age":28,"activities":[-1,211,50,700],"p_id":1956375,"possibilities":["HOME","JOB","SHOPPING","HOME"],"p_abo":false,"p_group":9},{"total_distance":10852.802,"p_sex":2,"scheme_id":20470,"p_age":25,"activities":[-1,211,531],"p_id":1956376,"possibilities":["HOME","JOB","HOME"],"p_abo":true,"p_group":11}]},{"hh_id":1553189,"hh_has_child":true,"hh_members":4,"hh_cars":1,"hh_income":4315,"members":[{"total_distance":56958.523,"p_sex":2,"scheme_id":20856,"p_age":41,"activities":[-1,211,700,211,700],"p_id":1956407,"possibilities":["HOME","JOB","HOME","JOB","HOME"],"p_abo":true,"p_group":11},{"total_distance":30625.754,"p_sex":1,"scheme_id":6134,"p_age":36,"activities":[-1,211,700,211,631,722],"p_id":1956408,"possibilities":["HOME","JOB","HOME","JOB","SETTLEMENT","HOME"],"p_abo":false,"p_group":9},{"total_distance":30816.605,"p_sex":1,"scheme_id":35588,"p_age":10,"activities":[-1,410,700,722,50,700,722,711],"p_id":1956405,"possibilities":["HOME","EDUCATION","HOME","LEISURE","SHOPPING","HOME","LEISURE","HOME"],"p_abo":true,"p_group":1}]}]