[{"hh_id":1331387,"hh_has_child":false,"hh_members":1,"hh_cars":0,"hh_income":1189,"members":[{"total_distance":2923.462,"p_sex":2,"scheme_id":12649,"p_age":66,"activities":[-1,32,531,32,531],"p_id":1562364,"possibilities":["HOME","SETTLEMENT","HOME","SETTLEMENT","HOME"],"p_abo":true,"p_group":28}]},{"hh_id":1331412,"hh_has_child":false,"hh_members":1,"hh_cars":0,"hh_income":988,"members":[{"total_distance":7691.4023,"p_sex":2,"scheme_id":22919,"p_age":71,"activities":[-1,522,10,724,10],"p_id":1562389,"possibilities":["HOME","SETTLEMENT","HOME","LEISURE","HOME"],"p_abo":false,"p_group":28}]},{"hh_id":1331415,"hh_has_child":false,"hh_members":1,"hh_cars":0,"hh_income":1467,"members":[{"total_distance":40479.82,"p_sex":2,"scheme_id":25063,"p_age":66,"activities":[-1,522,522,631,700,522,700,724,711],"p_id":1562392,"possibilities":["HOME","SETTLEMENT","SETTLEMENT","SETTLEMENT","HOME","SETTLEMENT","HOME","LEISURE","HOME"],"p_abo":false,"p_group":28}]},{"hh_id":1331435,"hh_has_child":false,"hh_members":1,"hh_cars":0,"hh_income":927,"members":[{"total_distance":43408.89,"p_sex":2,"scheme_id":8306,"p_age":71,"activities":[-1,640,10,640,10],"p_id":1562412,"possibilities":["HOME","LEISURE","HOME","LEISURE","HOME"],"p_abo":false,"p_group":28}]},{"hh_id":1331448,"hh_has_child":false,"hh_members":1,"hh_cars":0,"hh_income":1350,"members":[{"total_distance":19834.277,"p_sex":2,"scheme_id":24783,"p_age":71,"activities":[-1,611,10,800,531,800,299,522,10,631,700,724,700],"p_id":1562425,"possibilities":["HOME","SETTLEMENT","HOME","LEISURE","HOME","LEISURE","HOME","SETTLEMENT","HOME","SETTLEMENT","HOME","LEISURE","HOME"],"p_abo":true,"p_group":28}]}]