[{"hh_id":1061077,"hh_has_child":false,"hh_members":2,"hh_cars":2,"hh_income":1593,"members":[{"total_distance":4136.897,"p_sex":2,"scheme_id":34590,"p_age":74,"activities":[-1,631,531],"p_id":1177431,"possibilities":["HOME","SETTLEMENT","HOME"],"p_abo":false,"p_group":27},{"total_distance":17326.17,"p_sex":1,"scheme_id":10276,"p_age":60,"activities":[-1,211,10,800,10,800,10,800,10,300,10],"p_id":1177430,"possibilities":["HOME","JOB","HOME","LEISURE","HOME","LEISURE","HOME","LEISURE","HOME","LEISURE","HOME"],"p_abo":false,"p_group":17}]},{"hh_id":1061079,"hh_has_child":false,"hh_members":2,"hh_cars":1,"hh_income":2028,"members":[{"total_distance":0.0,"p_sex":2,"scheme_id":9296,"p_age":54,"activities":[],"p_id":1177435,"possibilities":[],"p_abo":false,"p_group":23},{"total_distance":24155.396,"p_sex":1,"scheme_id":22911,"p_age":40,"activities":[-1,522,50,10,722,299],"p_id":1177434,"possibilities":["HOME","SETTLEMENT","SHOPPING","HOME","LEISURE","HOME"],"p_abo":false,"p_group":13}]},{"hh_id":1061085,"hh_has_child":false,"hh_members":2,"hh_cars":2,"hh_income":1976,"members":[{"total_distance":31679.988,"p_sex":2,"scheme_id":17830,"p_age":69,"activities":[-1,611,531,50,700,800,531,800,722,800,10,800,700],"p_id":1177447,"possibilities":["HOME","SETTLEMENT","HOME","SHOPPING","HOME","LEISURE","HOME","LEISURE","LEISURE","LEISURE","HOME","LEISURE","HOME"],"p_abo":false,"p_group":27},{"total_distance":6202.6206,"p_sex":1,"scheme_id":26165,"p_age":54,"activities":[-1,50,700],"p_id":1177446,"possibilities":["HOME","SHOPPING","HOME"],"p_abo":false,"p_group":21}]},{"hh_id":1061093,"hh_has_child":false,"hh_members":2,"hh_cars":2,"hh_income":4227,"members":[{"total_distance":62723.42,"p_sex":2,"scheme_id":34700,"p_age":61,"activities":[-1,50,10,231,700,211,700,724,700],"p_id":1177463,"possibilities":["HOME","SHOPPING","HOME","LEISURE","HOME","JOB","HOME","LEISURE","HOME"],"p_abo":true,"p_group":19},{"total_distance":4230.4263,"p_sex":1,"scheme_id":5188,"p_age":46,"activities":[-1,50,10,50,10],"p_id":1177462,"possibilities":["HOME","SHOPPING","HOME","SHOPPING","HOME"],"p_abo":true,"p_group":21}]},{"hh_id":1061096,"hh_has_child":false,"hh_members":2,"hh_cars":1,"hh_income":1347,"members":[{"total_distance":21986.45,"p_sex":2,"scheme_id":27106,"p_age":76,"activities":[-1,611,10,800,700,50,700,722,531],"p_id":1177469,"possibilities":["HOME","SETTLEMENT","HOME","LEISURE","HOME","SHOPPING","HOME","LEISURE","HOME"],"p_abo":true,"p_group":31},{"total_distance":7884.219,"p_sex":1,"scheme_id":2800,"p_age":62,"activities":[-1,50,50,531,611,10],"p_id":1177468,"possibilities":["HOME","SHOPPING","SHOPPING","HOME","SETTLEMENT","HOME"],"p_abo":true,"p_group":17}]}]