[{"hh_id":1056967,"hh_has_child":false,"hh_members":2,"hh_cars":2,"hh_income":1552,"members":[{"total_distance":14340.156,"p_sex":2,"scheme_id":2798,"p_age":37,"activities":[-1,640,700,50,50,531,722,531],"p_id":1169211,"possibilities":["HOME","LEISURE","HOME","SHOPPING","SHOPPING","HOME","LEISURE","HOME"],"p_abo":true,"p_group":11},{"total_distance":12507.82,"p_sex":1,"scheme_id":21884,"p_age":26,"activities":[-1,411,299],"p_id":1169210,"possibilities":["HOME","EDUCATION","HOME"],"p_abo":true,"p_group":2}]},{"hh_id":1056979,"hh_has_child":false,"hh_members":2,"hh_cars":1,"hh_income":3330,"members":[{"total_distance":5289.3203,"p_sex":2,"scheme_id":17062,"p_age":41,"activities":[-1,631,531],"p_id":1169235,"possibilities":["HOME","SETTLEMENT","HOME"],"p_abo":true,"p_group":15},{"total_distance":55613.42,"p_sex":1,"scheme_id":30913,"p_age":38,"activities":[-1,211,522,211,799,724,700],"p_id":1169234,"possibilities":["HOME","JOB","SETTLEMENT","JOB","OTHER","LEISURE","HOME"],"p_abo":false,"p_group":9}]},{"hh_id":1056980,"hh_has_child":false,"hh_members":2,"hh_cars":0,"hh_income":1251,"members":[{"total_distance":25190.182,"p_sex":2,"scheme_id":21628,"p_age":67,"activities":[-1,522,10,32,800,299,211,10,32,711],"p_id":1169236,"possibilities":["HOME","SETTLEMENT","HOME","SETTLEMENT","LEISURE","HOME","JOB","HOME","SETTLEMENT","HOME"],"p_abo":true,"p_group":28},{"total_distance":0.0,"p_sex":1,"scheme_id":30478,"p_age":53,"activities":[],"p_id":1169237,"possibilities":[],"p_abo":false,"p_group":22}]},{"hh_id":1057009,"hh_has_child":false,"hh_members":2,"hh_cars":1,"hh_income":3126,"members":[{"total_distance":19901.553,"p_sex":2,"scheme_id":34203,"p_age":32,"activities":[-1,211,700,50,700],"p_id":1169295,"possibilities":["HOME","JOB","HOME","SHOPPING","HOME"],"p_abo":false,"p_group":11},{"total_distance":4184.7915,"p_sex":1,"scheme_id":31252,"p_age":29,"activities":[-1,411,711],"p_id":1169294,"possibilities":["HOME","EDUCATION","HOME"],"p_abo":false,"p_group":2}]},{"hh_id":1057016,"hh_has_child":false,"hh_members":2,"hh_cars":2,"hh_income":2091,"members":[{"total_distance":3585.3574,"p_sex":2,"scheme_id":11469,"p_age":54,"activities":[-1,50,10,799,700],"p_id":1169309,"possibilities":["HOME","SHOPPING","HOME","OTHER","HOME"],"p_abo":false,"p_group":23},{"total_distance":20054.082,"p_sex":1,"scheme_id":1472,"p_age":42,"activities":[-1,640,531,740,10,32,640,711],"p_id":1169308,"possibilities":["HOME","LEISURE","HOME","OTHER","HOME","SETTLEMENT","LEISURE","HOME"],"p_abo":true,"p_group":9}]}]