[{"hh_id":1194041,"hh_has_child":false,"hh_members":3,"hh_cars":0,"hh_income":1523,"members":[{"total_distance":420.42648,"p_sex":1,"scheme_id":24949,"p_age":42,"activities":[-1,50,10],"p_id":1368791,"possibilities":["HOME","SHOPPING","HOME"],"p_abo":true,"p_group":10},{"total_distance":11690.118,"p_sex":2,"scheme_id":17404,"p_age":42,"activities":[-1,32,531,50,299,611,711],"p_id":1368792,"possibilities":["HOME","SETTLEMENT","HOME","SHOPPING","HOME","SETTLEMENT","HOME"],"p_abo":true,"p_group":16},{"total_distance":30495.58,"p_sex":2,"scheme_id":31754,"p_age":22,"activities":[-1,211,720,211,299,522,10],"p_id":1368790,"possibilities":["HOME","JOB","LEISURE","JOB","HOME","SETTLEMENT","HOME"],"p_abo":true,"p_group":4}]},{"hh_id":1194048,"hh_has_child":false,"hh_members":3,"hh_cars":0,"hh_income":1048,"members":[{"total_distance":22775.764,"p_sex":1,"scheme_id":35235,"p_age":44,"activities":[-1,410,700,640,531,631,10,720,700,640,531],"p_id":1368812,"possibilities":["HOME","EDUCATION","HOME","LEISURE","HOME","SETTLEMENT","HOME","LEISURE","HOME","LEISURE","HOME"],"p_abo":false,"p_group":10},{"total_distance":75404.6,"p_sex":2,"scheme_id":12480,"p_age":44,"activities":[-1,522,700,640,10,50,720,720,700,640,531,640,531],"p_id":1368813,"possibilities":["HOME","SETTLEMENT","HOME","LEISURE","HOME","SHOPPING","LEISURE","LEISURE","HOME","LEISURE","HOME","LEISURE","HOME"],"p_abo":true,"p_group":16},{"total_distance":0.0,"p_sex":2,"scheme_id":22533,"p_age":18,"activities":[],"p_id":1368811,"possibilities":[],"p_abo":false,"p_group":7}]},{"hh_id":1194059,"hh_has_child":false,"hh_members":3,"hh_cars":1,"hh_income":7334,"members":[{"total_distance":8502.829,"p_sex":2,"scheme_id":26395,"p_age":54,"activities":[-1,800,10,512,10,800,700],"p_id":1368846,"possibilities":["HOME","LEISURE","HOME","LEISURE","HOME","LEISURE","HOME"],"p_abo":false,"p_group":23},{"total_distance":27952.656,"p_sex":1,"scheme_id":29253,"p_age":53,"activities":[-1,211,531],"p_id":1368845,"possibilities":["HOME","JOB","HOME"],"p_abo":false,"p_group":17},{"total_distance":10880.767,"p_sex":2,"scheme_id":1722,"p_age":21,"activities":[-1,211,10,611,700],"p_id":1368844,"possibilities":["HOME","JOB","HOME","SETTLEMENT","HOME"],"p_abo":true,"p_group":2}]},{"hh_id":1194068,"hh_has_child":false,"hh_members":3,"hh_cars":1,"hh_income":4436,"members":[{"total_distance":7672.7617,"p_sex":1,"scheme_id":28811,"p_age":63,"activities":[-1,211,531],"p_id":1368872,"possibilities":["HOME","JOB","HOME"],"p_abo":true,"p_group":17},{"total_distance":38455.438,"p_sex":2,"scheme_id":8834,"p_age":63,"activities":[-1,50,10,724,10],"p_id":1368873,"possibilities":["HOME","SHOPPING","HOME","LEISURE","HOME"],"p_abo":true,"p_group":23},{"total_distance":26174.477,"p_sex":2,"scheme_id":11350,"p_age":24,"activities":[-1,522,50,799,50,10,631,700,720,10],"p_id":1368871,"possibilities":["HOME","SETTLEMENT","SHOPPING","OTHER","SHOPPING","HOME","SETTLEMENT","HOME","LEISURE","HOME"],"p_abo":true,"p_group":8}]},{"hh_id":1194069,"hh_has_child":false,"hh_members":3,"hh_cars":2,"hh_income":2428,"members":[{"total_distance":1178.7542,"p_sex":2,"scheme_id":3731,"p_age":59,"activities":[-1,50,10],"p_id":1368876,"possibilities":["HOME","SHOPPING","HOME"],"p_abo":false,"p_group":23},{"total_distance":13329.707,"p_sex":1,"scheme_id":32194,"p_age":56,"activities":[-1,211,700],"p_id":1368875,"possibilities":["HOME","JOB","HOME"],"p_abo":true,"p_group":17},{"total_distance":72027.51,"p_sex":1,"scheme_id":7911,"p_age":20,"activities":[-1,640,299,410,720,511,410,299],"p_id":1368874,"possibilities":["HOME","LEISURE","HOME","EDUCATION","LEISURE","HOME","EDUCATION","HOME"],"p_abo":true,"p_group":1}]}]