[{"hh_id":1258347,"hh_has_child":false,"hh_members":1,"hh_cars":0,"hh_income":755,"members":[{"total_distance":6520.0723,"p_sex":1,"scheme_id":28736,"p_age":37,"activities":[-1,300,631,711],"p_id":1489328,"possibilities":["HOME","LEISURE","SETTLEMENT","HOME"],"p_abo":true,"p_group":14}]},{"hh_id":1258361,"hh_has_child":false,"hh_members":1,"hh_cars":0,"hh_income":873,"members":[{"total_distance":12942.275,"p_sex":1,"scheme_id":16154,"p_age":27,"activities":[-1,211,10,799,700],"p_id":1489342,"possibilities":["HOME","JOB","HOME","OTHER","HOME"],"p_abo":true,"p_group":10}]},{"hh_id":1258379,"hh_has_child":false,"hh_members":1,"hh_cars":0,"hh_income":883,"members":[{"total_distance":41055.36,"p_sex":1,"scheme_id":7994,"p_age":33,"activities":[-1,720,211,700,300,700],"p_id":1489360,"possibilities":["HOME","LEISURE","JOB","HOME","LEISURE","HOME"],"p_abo":true,"p_group":10}]},{"hh_id":1258409,"hh_has_child":false,"hh_members":1,"hh_cars":0,"hh_income":828,"members":[{"total_distance":4533.997,"p_sex":1,"scheme_id":20502,"p_age":34,"activities":[-1,640,531,640,711],"p_id":1489390,"possibilities":["HOME","LEISURE","HOME","LEISURE","HOME"],"p_abo":true,"p_group":14}]},{"hh_id":1258411,"hh_has_child":false,"hh_members":1,"hh_cars":1,"hh_income":819,"members":[{"total_distance":25743.354,"p_sex":1,"scheme_id":26283,"p_age":27,"activities":[-1,800,10,800,10,800,711,800,711],"p_id":1489392,"possibilities":["HOME","LEISURE","HOME","LEISURE","HOME","LEISURE","HOME","LEISURE","HOME"],"p_abo":false,"p_group":13}]}]