[{"hh_id":1461677,"hh_has_child":false,"hh_members":1,"hh_cars":0,"hh_income":1141,"members":[{"total_distance":18558.389,"p_sex":1,"scheme_id":20808,"p_age":30,"activities":[-1,211,211,211,531],"p_id":1829387,"possibilities":["HOME","JOB","JOB","JOB","HOME"],"p_abo":true,"p_group":10}]},{"hh_id":1461711,"hh_has_child":false,"hh_members":1,"hh_cars":0,"hh_income":1327,"members":[{"total_distance":2417.0972,"p_sex":1,"scheme_id":22200,"p_age":43,"activities":[-1,50,50,10],"p_id":1829421,"possibilities":["HOME","SHOPPING","SHOPPING","HOME"],"p_abo":false,"p_group":10}]},{"hh_id":1461719,"hh_has_child":false,"hh_members":1,"hh_cars":1,"hh_income":819,"members":[{"total_distance":8043.85,"p_sex":1,"scheme_id":4752,"p_age":29,"activities":[-1,211,299],"p_id":1829429,"possibilities":["HOME","JOB","HOME"],"p_abo":false,"p_group":9}]},{"hh_id":1461736,"hh_has_child":false,"hh_members":1,"hh_cars":0,"hh_income":1495,"members":[{"total_distance":5117.6885,"p_sex":1,"scheme_id":4697,"p_age":33,"activities":[-1,611,10,724,711],"p_id":1829446,"possibilities":["HOME","SETTLEMENT","HOME","LEISURE","HOME"],"p_abo":false,"p_group":10}]},{"hh_id":1461740,"hh_has_child":false,"hh_members":1,"hh_cars":0,"hh_income":891,"members":[{"total_distance":11420.465,"p_sex":1,"scheme_id":19635,"p_age":35,"activities":[-1,522,50,10,50,10],"p_id":1829450,"possibilities":["HOME","SETTLEMENT","SHOPPING","HOME","SHOPPING","HOME"],"p_abo":false,"p_group":14}]}]