[{"hh_id":1108358,"hh_has_child":false,"hh_members":1,"hh_cars":1,"hh_income":1520,"members":[{"total_distance":7088.793,"p_sex":1,"scheme_id":20973,"p_age":38,"activities":[-1,211,700],"p_id":1241634,"possibilities":["HOME","JOB","HOME"],"p_abo":false,"p_group":9}]},{"hh_id":1108374,"hh_has_child":false,"hh_members":1,"hh_cars":0,"hh_income":1362,"members":[{"total_distance":10380.007,"p_sex":1,"scheme_id":18324,"p_age":33,"activities":[-1,50,700,50,531,724,711],"p_id":1241650,"possibilities":["HOME","SHOPPING","HOME","SHOPPING","HOME","LEISURE","HOME"],"p_abo":false,"p_group":14}]},{"hh_id":1108383,"hh_has_child":false,"hh_members":1,"hh_cars":1,"hh_income":1140,"members":[{"total_distance":2375.1257,"p_sex":1,"scheme_id":31585,"p_age":32,"activities":[-1,211,700],"p_id":1241659,"possibilities":["HOME","JOB","HOME"],"p_abo":false,"p_group":9}]},{"hh_id":1108384,"hh_has_child":false,"hh_members":1,"hh_cars":0,"hh_income":1437,"members":[{"total_distance":14548.089,"p_sex":1,"scheme_id":17749,"p_age":38,"activities":[-1,211,700,720,10,50,50,700],"p_id":1241660,"possibilities":["HOME","JOB","HOME","LEISURE","HOME","SHOPPING","SHOPPING","HOME"],"p_abo":false,"p_group":10}]},{"hh_id":1108401,"hh_has_child":false,"hh_members":1,"hh_cars":1,"hh_income":874,"members":[{"total_distance":22593.957,"p_sex":1,"scheme_id":31902,"p_age":36,"activities":[-1,211,720,700],"p_id":1241677,"possibilities":["HOME","JOB","LEISURE","HOME"],"p_abo":false,"p_group":9}]}]