[{"hh_id":1336707,"hh_has_child":false,"hh_members":1,"hh_cars":0,"hh_income":1050,"members":[{"total_distance":34170.2,"p_sex":2,"scheme_id":22336,"p_age":86,"activities":[-1,522,631,299],"p_id":1567683,"possibilities":["HOME","SETTLEMENT","SETTLEMENT","HOME"],"p_abo":false,"p_group":32}]},{"hh_id":1336723,"hh_has_child":false,"hh_members":3,"hh_cars":1,"hh_income":1931,"members":[{"total_distance":13254.547,"p_sex":1,"scheme_id":35107,"p_age":88,"activities":[-1,50,631,50,32,50,531,32,700],"p_id":1567716,"possibilities":["HOME","SHOPPING","SETTLEMENT","SHOPPING","SETTLEMENT","SHOPPING","HOME","SETTLEMENT","HOME"],"p_abo":false,"p_group":29},{"total_distance":7011.3564,"p_sex":1,"scheme_id":35053,"p_age":87,"activities":[-1,720,511],"p_id":1567717,"possibilities":["HOME","LEISURE","HOME"],"p_abo":false,"p_group":29},{"total_distance":36804.22,"p_sex":1,"scheme_id":24649,"p_age":75,"activities":[-1,50,50,531,721,720,10],"p_id":1567715,"possibilities":["HOME","SHOPPING","SHOPPING","HOME","LEISURE","LEISURE","HOME"],"p_abo":false,"p_group":29}]},{"hh_id":1336747,"hh_has_child":false,"hh_members":3,"hh_cars":0,"hh_income":1731,"members":[{"total_distance":6510.7456,"p_sex":1,"scheme_id":11215,"p_age":84,"activities":[-1,50,10],"p_id":1567787,"possibilities":["HOME","SHOPPING","HOME"],"p_abo":true,"p_group":30},{"total_distance":33351.676,"p_sex":1,"scheme_id":14628,"p_age":81,"activities":[-1,231,50,700,611,700],"p_id":1567789,"possibilities":["HOME","LEISURE","SHOPPING","HOME","SETTLEMENT","HOME"],"p_abo":false,"p_group":30}]},{"hh_id":1336777,"hh_has_child":false,"hh_members":3,"hh_cars":0,"hh_income":802,"members":[{"total_distance":15566.6,"p_sex":1,"scheme_id":13985,"p_age":88,"activities":[-1,50,50,10,721,700],"p_id":1567878,"possibilities":["HOME","SHOPPING","SHOPPING","HOME","LEISURE","HOME"],"p_abo":false,"p_group":30},{"total_distance":4533.9624,"p_sex":1,"scheme_id":15563,"p_age":86,"activities":[-1,522,700,800,10],"p_id":1567879,"possibilities":["HOME","SETTLEMENT","HOME","LEISURE","HOME"],"p_abo":true,"p_group":30},{"total_distance":17263.457,"p_sex":1,"scheme_id":21255,"p_age":83,"activities":[-1,50,10,800,700],"p_id":1567877,"possibilities":["HOME","SHOPPING","HOME","LEISURE","HOME"],"p_abo":false,"p_group":30}]},{"hh_id":1336780,"hh_has_child":false,"hh_members":3,"hh_cars":2,"hh_income":3267,"members":[{"total_distance":18022.297,"p_sex":1,"scheme_id":18690,"p_age":87,"activities":[-1,211,700],"p_id":1567888,"possibilities":["HOME","JOB","HOME"],"p_abo":true,"p_group":29},{"total_distance":5973.9136,"p_sex":1,"scheme_id":28462,"p_age":85,"activities":[-1,50,700,720,700],"p_id":1567886,"possibilities":["HOME","SHOPPING","HOME","LEISURE","HOME"],"p_abo":true,"p_group":29},{"total_distance":25320.354,"p_sex":1,"scheme_id":11650,"p_age":78,"activities":[-1,721,700,522,62,10,512,10,522,700],"p_id":1567887,"possibilities":["HOME","LEISURE","HOME","SETTLEMENT","JOB","HOME","LEISURE","HOME","SETTLEMENT","HOME"],"p_abo":false,"p_group":29}]}]