[{"hh_id":1051996,"hh_has_child":false,"hh_members":2,"hh_cars":1,"hh_income":6606,"members":[{"total_distance":5159.335,"p_sex":2,"scheme_id":31313,"p_age":34,"activities":[-1,722,700],"p_id":1159269,"possibilities":["HOME","LEISURE","HOME"],"p_abo":false,"p_group":11},{"total_distance":8142.9844,"p_sex":1,"scheme_id":33801,"p_age":33,"activities":[-1,211,531,522,531,722,711],"p_id":1159268,"possibilities":["HOME","JOB","HOME","SETTLEMENT","HOME","LEISURE","HOME"],"p_abo":false,"p_group":9}]},{"hh_id":1052003,"hh_has_child":false,"hh_members":2,"hh_cars":1,"hh_income":2118,"members":[{"total_distance":23302.98,"p_sex":2,"scheme_id":13241,"p_age":56,"activities":[-1,211,531,211,10,724,700],"p_id":1159283,"possibilities":["HOME","JOB","HOME","JOB","HOME","LEISURE","HOME"],"p_abo":true,"p_group":19},{"total_distance":18809.389,"p_sex":1,"scheme_id":21625,"p_age":41,"activities":[-1,211,531,211,531,740,700],"p_id":1159282,"possibilities":["HOME","JOB","HOME","JOB","HOME","OTHER","HOME"],"p_abo":true,"p_group":9}]},{"hh_id":1052008,"hh_has_child":false,"hh_members":2,"hh_cars":1,"hh_income":2624,"members":[{"total_distance":8003.741,"p_sex":2,"scheme_id":3404,"p_age":63,"activities":[-1,611,740,720,10,300,10],"p_id":1159293,"possibilities":["HOME","SETTLEMENT","OTHER","LEISURE","HOME","LEISURE","HOME"],"p_abo":false,"p_group":23},{"total_distance":3187.353,"p_sex":1,"scheme_id":22190,"p_age":48,"activities":[-1,640,10],"p_id":1159292,"possibilities":["HOME","LEISURE","HOME"],"p_abo":false,"p_group":21}]},{"hh_id":1052015,"hh_has_child":false,"hh_members":2,"hh_cars":1,"hh_income":3512,"members":[{"total_distance":44676.08,"p_sex":2,"scheme_id":25904,"p_age":37,"activities":[-1,522,720,50,531],"p_id":1159307,"possibilities":["HOME","SETTLEMENT","LEISURE","SHOPPING","HOME"],"p_abo":false,"p_group":15},{"total_distance":10409.613,"p_sex":1,"scheme_id":27162,"p_age":29,"activities":[-1,211,10],"p_id":1159306,"possibilities":["HOME","JOB","HOME"],"p_abo":false,"p_group":9}]},{"hh_id":1052024,"hh_has_child":false,"hh_members":2,"hh_cars":0,"hh_income":893,"members":[{"total_distance":21219.16,"p_sex":2,"scheme_id":19354,"p_age":82,"activities":[-1,800,700,522,720,50,800,531,800,10],"p_id":1159324,"possibilities":["HOME","LEISURE","HOME","SETTLEMENT","LEISURE","SHOPPING","LEISURE","HOME","LEISURE","HOME"],"p_abo":true,"p_group":32},{"total_distance":6382.892,"p_sex":1,"scheme_id":23758,"p_age":71,"activities":[-1,50,531,32,700,799,700],"p_id":1159325,"possibilities":["HOME","SHOPPING","HOME","SETTLEMENT","HOME","OTHER","HOME"],"p_abo":false,"p_group":26}]}]