[{"hh_id":1545705,"hh_has_child":false,"hh_members":5,"hh_cars":0,"hh_income":831,"members":[{"total_distance":49135.36,"p_sex":2,"scheme_id":11609,"p_age":41,"activities":[-1,631,722,800,10],"p_id":1924756,"possibilities":["HOME","SETTLEMENT","LEISURE","LEISURE","HOME"],"p_abo":false,"p_group":16},{"total_distance":3258.433,"p_sex":2,"scheme_id":33870,"p_age":23,"activities":[-1,411,531],"p_id":1924753,"possibilities":["HOME","EDUCATION","HOME"],"p_abo":true,"p_group":2},{"total_distance":2864.0403,"p_sex":1,"scheme_id":13035,"p_age":17,"activities":[-1,50,299],"p_id":1924754,"possibilities":["HOME","SHOPPING","HOME"],"p_abo":true,"p_group":7},{"total_distance":0.0,"p_sex":1,"scheme_id":21233,"p_age":9,"activities":[],"p_id":1924755,"possibilities":[],"p_abo":true,"p_group":1}]},{"hh_id":1545709,"hh_has_child":false,"hh_members":5,"hh_cars":1,"hh_income":3695,"members":[{"total_distance":25576.137,"p_sex":2,"scheme_id":16066,"p_age":60,"activities":[-1,211,531,720,700],"p_id":1924776,"possibilities":["HOME","JOB","HOME","LEISURE","HOME"],"p_abo":true,"p_group":23},{"total_distance":26987.363,"p_sex":1,"scheme_id":32556,"p_age":60,"activities":[-1,50,721,211,531,211,531,211,700],"p_id":1924777,"possibilities":["HOME","SHOPPING","LEISURE","JOB","HOME","JOB","HOME","JOB","HOME"],"p_abo":false,"p_group":17},{"total_distance":15396.982,"p_sex":2,"scheme_id":33799,"p_age":23,"activities":[-1,411,511,50,299],"p_id":1924774,"possibilities":["HOME","EDUCATION","HOME","SHOPPING","HOME"],"p_abo":true,"p_group":2},{"total_distance":37687.84,"p_sex":1,"scheme_id":14228,"p_age":22,"activities":[-1,722,10,211,531,211,700,50,631,611,720,700],"p_id":1924775,"possibilities":["HOME","LEISURE","HOME","JOB","HOME","JOB","HOME","SHOPPING","SETTLEMENT","SETTLEMENT","LEISURE","HOME"],"p_abo":false,"p_group":3},{"total_distance":5119.6113,"p_sex":1,"scheme_id":20707,"p_age":21,"activities":[-1,799,531,721,700],"p_id":1924773,"possibilities":["HOME","OTHER","HOME","LEISURE","HOME"],"p_abo":true,"p_group":6}]},{"hh_id":1545724,"hh_has_child":true,"hh_members":5,"hh_cars":1,"hh_income":3415,"members":[{"total_distance":18833.271,"p_sex":2,"scheme_id":31814,"p_age":27,"activities":[-1,522,700,800,531,640,10],"p_id":1924851,"possibilities":["HOME","SETTLEMENT","HOME","LEISURE","HOME","LEISURE","HOME"],"p_abo":false,"p_group":11},{"total_distance":66710.49,"p_sex":1,"scheme_id":2295,"p_age":27,"activities":[-1,800,700,50,10,721,700],"p_id":1924852,"possibilities":["HOME","LEISURE","HOME","SHOPPING","HOME","LEISURE","HOME"],"p_abo":true,"p_group":2},{"total_distance":3964.5942,"p_sex":1,"scheme_id":11000,"p_age":7,"activities":[-1,640,10,522,10],"p_id":1924850,"possibilities":["HOME","LEISURE","HOME","SETTLEMENT","HOME"],"p_abo":true,"p_group":1}]},{"hh_id":1545725,"hh_has_child":false,"hh_members":5,"hh_cars":1,"hh_income":3318,"members":[{"total_distance":35838.094,"p_sex":1,"scheme_id":30952,"p_age":46,"activities":[-1,211,700,522,800,531],"p_id":1924857,"possibilities":["HOME","JOB","HOME","SETTLEMENT","LEISURE","HOME"],"p_abo":false,"p_group":17},{"total_distance":3653.7075,"p_sex":2,"scheme_id":13719,"p_age":45,"activities":[-1,800,700],"p_id":1924856,"possibilities":["HOME","LEISURE","HOME"],"p_abo":false,"p_group":23},{"total_distance":57872.266,"p_sex":2,"scheme_id":11830,"p_age":23,"activities":[-1,211,531,211,700,721,700,721,720,721,711],"p_id":1924855,"possibilities":["HOME","JOB","HOME","JOB","HOME","LEISURE","HOME","LEISURE","LEISURE","LEISURE","HOME"],"p_abo":false,"p_group":2},{"total_distance":10963.541,"p_sex":1,"scheme_id":12043,"p_age":19,"activities":[-1,410,700],"p_id":1924853,"possibilities":["HOME","EDUCATION","HOME"],"p_abo":true,"p_group":6},{"total_distance":47927.47,"p_sex":2,"scheme_id":3346,"p_age":9,"activities":[-1,410,700,410,711],"p_id":1924854,"possibilities":["HOME","EDUCATION","HOME","EDUCATION","HOME"],"p_abo":true,"p_group":1}]},{"hh_id":1545741,"hh_has_child":false,"hh_members":5,"hh_cars":1,"hh_income":4751,"members":[{"total_distance":2905.2246,"p_sex":2,"scheme_id":14355,"p_age":54,"activities":[-1,211,531],"p_id":1924936,"possibilities":["HOME","JOB","HOME"],"p_abo":true,"p_group":19},{"total_distance":13513.324,"p_sex":1,"scheme_id":9907,"p_age":54,"activities":[-1,800,211,531,211,531],"p_id":1924937,"possibilities":["HOME","LEISURE","JOB","HOME","JOB","HOME"],"p_abo":false,"p_group":17},{"total_distance":752.3118,"p_sex":1,"scheme_id":25527,"p_age":22,"activities":[-1,231,700],"p_id":1924934,"possibilities":["HOME","LEISURE","HOME"],"p_abo":false,"p_group":3},{"total_distance":0.0,"p_sex":2,"scheme_id":25894,"p_age":19,"activities":[],"p_id":1924933,"possibilities":[],"p_abo":false,"p_group":8},{"total_distance":991.99255,"p_sex":2,"scheme_id":18380,"p_age":15,"activities":[-1,410,531],"p_id":1924935,"possibilities":["HOME","EDUCATION","HOME"],"p_abo":true,"p_group":1}]}]