[{"hh_id":1132949,"hh_has_child":false,"hh_members":1,"hh_cars":0,"hh_income":1554,"members":[{"total_distance":20361.963,"p_sex":1,"scheme_id":30442,"p_age":74,"activities":[-1,640,299,740,740,700],"p_id":1266223,"possibilities":["HOME","LEISURE","HOME","OTHER","OTHER","HOME"],"p_abo":false,"p_group":26}]},{"hh_id":1132960,"hh_has_child":false,"hh_members":1,"hh_cars":1,"hh_income":1265,"members":[{"total_distance":19136.895,"p_sex":1,"scheme_id":20787,"p_age":73,"activities":[-1,32,531,611,711],"p_id":1266234,"possibilities":["HOME","SETTLEMENT","HOME","SETTLEMENT","HOME"],"p_abo":false,"p_group":25}]},{"hh_id":1132965,"hh_has_child":false,"hh_members":1,"hh_cars":1,"hh_income":1030,"members":[{"total_distance":3214.6235,"p_sex":1,"scheme_id":17957,"p_age":74,"activities":[-1,740,10,50,10],"p_id":1266239,"possibilities":["HOME","OTHER","HOME","SHOPPING","HOME"],"p_abo":false,"p_group":25}]},{"hh_id":1132973,"hh_has_child":false,"hh_members":1,"hh_cars":1,"hh_income":845,"members":[{"total_distance":42156.8,"p_sex":1,"scheme_id":29089,"p_age":73,"activities":[-1,800,700,721,720,700,640,700],"p_id":1266247,"possibilities":["HOME","LEISURE","HOME","LEISURE","LEISURE","HOME","LEISURE","HOME"],"p_abo":true,"p_group":25}]},{"hh_id":1132974,"hh_has_child":false,"hh_members":1,"hh_cars":1,"hh_income":789,"members":[{"total_distance":10855.709,"p_sex":1,"scheme_id":8042,"p_age":69,"activities":[-1,740,10,611,10],"p_id":1266248,"possibilities":["HOME","OTHER","HOME","SETTLEMENT","HOME"],"p_abo":false,"p_group":25}]}]