[{"hh_id":1018563,"hh_has_child":true,"hh_members":3,"hh_cars":2,"hh_income":2024,"members":[{"total_distance":9512.789,"p_sex":1,"scheme_id":3996,"p_age":33,"activities":[-1,211,531,50,711],"p_id":1078837,"possibilities":["HOME","JOB","HOME","SHOPPING","HOME"],"p_abo":true,"p_group":9},{"total_distance":31284.03,"p_sex":2,"scheme_id":23052,"p_age":33,"activities":[-1,740,10,722,10,50,10,724,700],"p_id":1078838,"possibilities":["HOME","OTHER","HOME","LEISURE","HOME","SHOPPING","HOME","LEISURE","HOME"],"p_abo":false,"p_group":15}]},{"hh_id":1018567,"hh_has_child":false,"hh_members":3,"hh_cars":1,"hh_income":2248,"members":[{"total_distance":18269.04,"p_sex":1,"scheme_id":3651,"p_age":35,"activities":[-1,211,700,522,299],"p_id":1078849,"possibilities":["HOME","JOB","HOME","SETTLEMENT","HOME"],"p_abo":false,"p_group":9},{"total_distance":14155.641,"p_sex":2,"scheme_id":3351,"p_age":35,"activities":[-1,522,10,50,631,10],"p_id":1078850,"possibilities":["HOME","SETTLEMENT","HOME","SHOPPING","SETTLEMENT","HOME"],"p_abo":true,"p_group":11},{"total_distance":2017.2289,"p_sex":1,"scheme_id":19683,"p_age":10,"activities":[-1,410,531],"p_id":1078848,"possibilities":["HOME","EDUCATION","HOME"],"p_abo":true,"p_group":1}]},{"hh_id":1018579,"hh_has_child":false,"hh_members":3,"hh_cars":0,"hh_income":1099,"members":[{"total_distance":15232.328,"p_sex":1,"scheme_id":33929,"p_age":36,"activities":[-1,211,211,211,700],"p_id":1078885,"possibilities":["HOME","JOB","JOB","JOB","HOME"],"p_abo":false,"p_group":10},{"total_distance":42090.8,"p_sex":2,"scheme_id":7795,"p_age":36,"activities":[-1,50,800,50,32,711],"p_id":1078886,"possibilities":["HOME","SHOPPING","LEISURE","SHOPPING","SETTLEMENT","HOME"],"p_abo":false,"p_group":16},{"total_distance":10646.376,"p_sex":2,"scheme_id":30809,"p_age":6,"activities":[-1,410,531],"p_id":1078884,"possibilities":["HOME","EDUCATION","HOME"],"p_abo":true,"p_group":1}]},{"hh_id":1018582,"hh_has_child":false,"hh_members":3,"hh_cars":0,"hh_income":1778,"members":[{"total_distance":41523.87,"p_sex":2,"scheme_id":17340,"p_age":29,"activities":[-1,640,700],"p_id":1078894,"possibilities":["HOME","LEISURE","HOME"],"p_abo":false,"p_group":16},{"total_distance":27830.387,"p_sex":1,"scheme_id":31580,"p_age":29,"activities":[-1,722,711,799,50,720,700,720,700],"p_id":1078895,"possibilities":["HOME","LEISURE","HOME","OTHER","SHOPPING","LEISURE","HOME","LEISURE","HOME"],"p_abo":false,"p_group":14},{"total_distance":19043.086,"p_sex":2,"scheme_id":5939,"p_age":8,"activities":[-1,410,700,722,299,723,531],"p_id":1078893,"possibilities":["HOME","EDUCATION","HOME","LEISURE","HOME","LEISURE","HOME"],"p_abo":true,"p_group":1}]},{"hh_id":1018589,"hh_has_child":false,"hh_members":3,"hh_cars":0,"hh_income":1847,"members":[{"total_distance":20778.816,"p_sex":1,"scheme_id":15186,"p_age":36,"activities":[-1,211,700,50,10],"p_id":1078915,"possibilities":["HOME","JOB","HOME","SHOPPING","HOME"],"p_abo":true,"p_group":10},{"total_distance":602.8847,"p_sex":2,"scheme_id":14272,"p_age":36,"activities":[-1,50,700],"p_id":1078916,"possibilities":["HOME","SHOPPING","HOME"],"p_abo":false,"p_group":16},{"total_distance":9743.57,"p_sex":2,"scheme_id":4062,"p_age":11,"activities":[-1,50,531,50,711,723,723,700],"p_id":1078914,"possibilities":["HOME","SHOPPING","HOME","SHOPPING","HOME","LEISURE","LEISURE","HOME"],"p_abo":true,"p_group":1}]}]