[{"hh_id":1076201,"hh_has_child":false,"hh_members":2,"hh_cars":1,"hh_income":1276,"members":[{"total_distance":6112.3477,"p_sex":2,"scheme_id":19632,"p_age":72,"activities":[-1,50,700,50,50,531],"p_id":1207679,"possibilities":["HOME","SHOPPING","HOME","SHOPPING","SHOPPING","HOME"],"p_abo":true,"p_group":27},{"total_distance":61995.742,"p_sex":1,"scheme_id":29918,"p_age":63,"activities":[-1,800,10,720,700],"p_id":1207678,"possibilities":["HOME","LEISURE","HOME","LEISURE","HOME"],"p_abo":false,"p_group":17}]},{"hh_id":1076202,"hh_has_child":false,"hh_members":2,"hh_cars":1,"hh_income":2026,"members":[{"total_distance":14089.124,"p_sex":2,"scheme_id":8313,"p_age":84,"activities":[-1,50,10,50,10,722,700],"p_id":1207681,"possibilities":["HOME","SHOPPING","HOME","SHOPPING","HOME","LEISURE","HOME"],"p_abo":false,"p_group":31},{"total_distance":5240.329,"p_sex":1,"scheme_id":7654,"p_age":74,"activities":[-1,50,10,800,531,50,700],"p_id":1207680,"possibilities":["HOME","SHOPPING","HOME","LEISURE","HOME","SHOPPING","HOME"],"p_abo":false,"p_group":25}]},{"hh_id":1076209,"hh_has_child":false,"hh_members":2,"hh_cars":1,"hh_income":1739,"members":[{"total_distance":3687.7212,"p_sex":2,"scheme_id":15399,"p_age":56,"activities":[-1,640,700],"p_id":1207695,"possibilities":["HOME","LEISURE","HOME"],"p_abo":false,"p_group":23},{"total_distance":40054.016,"p_sex":1,"scheme_id":20823,"p_age":45,"activities":[-1,211,700,721,700],"p_id":1207694,"possibilities":["HOME","JOB","HOME","LEISURE","HOME"],"p_abo":false,"p_group":17}]},{"hh_id":1076221,"hh_has_child":false,"hh_members":2,"hh_cars":2,"hh_income":2864,"members":[{"total_distance":55494.35,"p_sex":2,"scheme_id":34305,"p_age":72,"activities":[-1,640,700,611,700,300,800,10,300,711],"p_id":1207719,"possibilities":["HOME","LEISURE","HOME","SETTLEMENT","HOME","LEISURE","LEISURE","HOME","LEISURE","HOME"],"p_abo":true,"p_group":27}]},{"hh_id":1076245,"hh_has_child":false,"hh_members":2,"hh_cars":2,"hh_income":1569,"members":[{"total_distance":11135.154,"p_sex":2,"scheme_id":1085,"p_age":28,"activities":[-1,410,700,724,711],"p_id":1207767,"possibilities":["HOME","EDUCATION","HOME","LEISURE","HOME"],"p_abo":false,"p_group":15},{"total_distance":8061.8496,"p_sex":1,"scheme_id":1998,"p_age":25,"activities":[-1,211,50,10],"p_id":1207766,"possibilities":["HOME","JOB","SHOPPING","HOME"],"p_abo":false,"p_group":9}]}]