[{"hh_id":1235777,"hh_has_child":false,"hh_members":2,"hh_cars":0,"hh_income":1076,"members":[{"total_distance":2245.6887,"p_sex":2,"scheme_id":35213,"p_age":65,"activities":[-1,522,531],"p_id":1463902,"possibilities":["HOME","SETTLEMENT","HOME"],"p_abo":false,"p_group":28},{"total_distance":10250.813,"p_sex":1,"scheme_id":19156,"p_age":50,"activities":[-1,721,531,211,211,211,299],"p_id":1463901,"possibilities":["HOME","LEISURE","HOME","JOB","JOB","JOB","HOME"],"p_abo":false,"p_group":18}]},{"hh_id":1235782,"hh_has_child":false,"hh_members":2,"hh_cars":0,"hh_income":1704,"members":[{"total_distance":2450.6597,"p_sex":2,"scheme_id":30399,"p_age":83,"activities":[-1,50,10,50,700],"p_id":1463912,"possibilities":["HOME","SHOPPING","HOME","SHOPPING","HOME"],"p_abo":false,"p_group":32},{"total_distance":10516.687,"p_sex":1,"scheme_id":28487,"p_age":69,"activities":[-1,640,700,631,631,10,631,700],"p_id":1463911,"possibilities":["HOME","LEISURE","HOME","SETTLEMENT","SETTLEMENT","HOME","SETTLEMENT","HOME"],"p_abo":true,"p_group":26}]},{"hh_id":1235789,"hh_has_child":false,"hh_members":2,"hh_cars":0,"hh_income":1153,"members":[{"total_distance":5551.9927,"p_sex":2,"scheme_id":14557,"p_age":62,"activities":[-1,722,711],"p_id":1463926,"possibilities":["HOME","LEISURE","HOME"],"p_abo":false,"p_group":24},{"total_distance":20174.908,"p_sex":1,"scheme_id":6358,"p_age":47,"activities":[-1,211,611,531,721,531],"p_id":1463925,"possibilities":["HOME","JOB","SETTLEMENT","HOME","LEISURE","HOME"],"p_abo":true,"p_group":22}]},{"hh_id":1235794,"hh_has_child":false,"hh_members":2,"hh_cars":0,"hh_income":1825,"members":[{"total_distance":0.0,"p_sex":2,"scheme_id":21786,"p_age":39,"activities":[],"p_id":1463936,"possibilities":[],"p_abo":false,"p_group":16},{"total_distance":7819.4707,"p_sex":1,"scheme_id":19818,"p_age":32,"activities":[-1,721,723,700],"p_id":1463935,"possibilities":["HOME","LEISURE","LEISURE","HOME"],"p_abo":false,"p_group":2}]},{"hh_id":1235797,"hh_has_child":false,"hh_members":2,"hh_cars":0,"hh_income":1700,"members":[{"total_distance":13480.77,"p_sex":2,"scheme_id":2927,"p_age":67,"activities":[-1,300,522,700,724,700],"p_id":1463942,"possibilities":["HOME","LEISURE","SETTLEMENT","HOME","LEISURE","HOME"],"p_abo":true,"p_group":28},{"total_distance":40031.06,"p_sex":1,"scheme_id":17743,"p_age":52,"activities":[-1,32,522,611,722,720,50,800,740,700],"p_id":1463941,"possibilities":["HOME","SETTLEMENT","SETTLEMENT","SETTLEMENT","LEISURE","LEISURE","SHOPPING","LEISURE","OTHER","HOME"],"p_abo":true,"p_group":22}]}]